4chan-thread-archiver
README.rst
archive-chan
archive-nabber
setup.py
thread-archiver
archive_chan.egg-info/PKG-INFO
archive_chan.egg-info/SOURCES.txt
archive_chan.egg-info/dependency_links.txt
archive_chan.egg-info/requires.txt
archive_chan.egg-info/top_level.txt
basc_archiver/__init__.py
basc_archiver/utils.py
basc_archiver/sites/__init__.py
basc_archiver/sites/base.py
basc_archiver/sites/fourchan.py
basc_archiver/sites/fuuka.py