Metadata-Version: 1.2
Name: archive-chan
Version: 0.1.4
Summary: Makes a complete hostable archive of imageboard threads including images, HTML, and JSON.
Home-page: https://github.com/shawwn/archive-chan
Author: Antonizoon Overtwater <antonizoon@bibanon.org>, Daniel Oaks <daniel@danieloaks.net>
Author-email: antonizoon@bibanon.org
Maintainer: Shawn Presser <twitter.com/theshawwn>
Maintainer-email: shawnpresser@gmail.com
License: UNKNOWN
Keywords: 4chan downloader images json dump
Platform: UNKNOWN
Classifier: Development Status :: 4 - Beta
Classifier: Intended Audience :: Developers
Classifier: Natural Language :: English
Classifier: Programming Language :: Python :: 2
Classifier: Programming Language :: Python :: 3
